pyqt_editable_list_widget/__init__.py
pyqt_editable_list_widget/editableListWidget.py
pyqt_editable_list_widget-0.0.11.dist-info/LICENSE
pyqt_editable_list_widget-0.0.11.dist-info/METADATA
pyqt_editable_list_widget-0.0.11.dist-info/WHEEL
pyqt_editable_list_widget-0.0.11.dist-info/top_level.txt
pyqt_editable_list_widget-0.0.11.dist-info/RECORD
