Metadata-Version: 2.1
Name: pyqt-editable-list-widget
Version: 0.0.11
Summary: Easily editable list widget
Home-page: https://github.com/yjg30737/pyqt-editable-list-widget.git
Author: Jung Gyu Yoon
Author-email: yjg30737@gmail.com
License: MIT
Platform: UNKNOWN
License-File: LICENSE
Requires-Dist: PyQt5 (>=5.8)
